CHANGELOG.rst
LICENSE
MANIFEST.in
README.rst
dev_requires.txt
requires.txt
setup.cfg
setup.py
tox.ini
daiquiri_rollbar/__init__.py
daiquiri_rollbar.egg-info/PKG-INFO
daiquiri_rollbar.egg-info/SOURCES.txt
daiquiri_rollbar.egg-info/dependency_links.txt
daiquiri_rollbar.egg-info/not-zip-safe
daiquiri_rollbar.egg-info/requires.txt
daiquiri_rollbar.egg-info/top_level.txt
daiquiri_rollbar/tests/__init__.py
daiquiri_rollbar/tests/test_invalid_rollbar_token.py
daiquiri_rollbar/tests/test_log_into_rollbar.py