Metadata-Version: 1.1
Name: daiquiri-rollbar
Version: 0.2.1
Summary: Easy way to integrate Rollbar into daiquiri
Home-page: https://gitlab.com/Jenselme/daiquiri-rollbar
Author: Julien Enselme
Author-email: jenselme@jujens.eu
License: MIT
Keywords: daiquiri logging rollbar
Platform: UNKNOWN
Classifier: Programming Language :: Python :: 3
Classifier: Intended Audience :: Developers
Classifier: License :: OSI Approved :: MIT License
Classifier: Topic :: System :: Logging
